pytest_unused_fixtures/__init__.py
pytest_unused_fixtures/decorators.py
pytest_unused_fixtures/options.py
pytest_unused_fixtures/plugin.py
pytest_unused_fixtures/xdist.py
pytest_unused_fixtures-0.3.1.dist-info/METADATA
pytest_unused_fixtures-0.3.1.dist-info/WHEEL
pytest_unused_fixtures-0.3.1.dist-info/entry_points.txt
pytest_unused_fixtures-0.3.1.dist-info/licenses/LICENSE
pytest_unused_fixtures-0.3.1.dist-info/RECORD
