Metadata-Version: 2.4
Name: pytest-unused-fixtures
Version: 0.3.1
Summary: A pytest plugin to list unused fixtures after a test run.
License: MIT
License-File: LICENSE
Keywords: pytest,fixtures
Author: Mikuláš Poul
Author-email: mikulaspoul@gmail.com
Requires-Python: >=3.9,<4.0
Classifier: Development Status :: 4 - Beta
Classifier: Framework :: Pytest
Classifier: Intended Audience :: Developers
Classifier: License :: OSI Approved :: MIT License
Classifier: Operating System :: OS Independent
Classifier: Programming Language :: Python :: 3
Classifier: Programming Language :: Python :: 3.9
Classifier: Programming Language :: Python :: 3.10
Classifier: Programming Language :: Python :: 3.11
Classifier: Programming Language :: Python :: 3.12
Classifier: Programming Language :: Python :: 3.13
Classifier: Programming Language :: Python :: 3.14
Classifier: Topic :: Software Development :: Testing
Requires-Dist: pytest (>7.3.2)
Project-URL: Repository, https://github.com/mikicz/pytest-unused-fixtures
